[
	{
    "id": 1,
    "priority": 1,
    "action": { "type": "redirect", "redirect": { "extensionPath": "/blocked.html" } },
    "condition": {
			"resourceTypes": ["main_frame","sub_frame","stylesheet","script","image","font","object","xmlhttprequest","ping","csp_report","media","websocket","webtransport","webbundle","other"],
			"urlFilter": "adxpartner.com"
		 }
  }, {
    "id": 2,
    "priority": 1,
    "action": { "type": "redirect", "redirect": { "extensionPath": "/blocked.html" } },
    "condition": {
			"resourceTypes": ["main_frame","sub_frame","stylesheet","script","image","font","object","xmlhttprequest","ping","csp_report","media","websocket","webtransport","webbundle","other"],
			"urlFilter": "deinseitensprung.club"
		 }
  }, {
    "id": 3,
    "priority": 1,
    "action": { "type": "redirect", "redirect": { "extensionPath": "/blocked.html" } },
    "condition": {
			"resourceTypes": ["main_frame","sub_frame","stylesheet","script","image","font","object","xmlhttprequest","ping","csp_report","media","websocket","webtransport","webbundle","other"],
			"urlFilter": "pornobombe.com"
		 }
  }, {
    "id": 4,
    "priority": 1,
    "action": { "type": "redirect", "redirect": { "extensionPath": "/blocked.html" } },
    "condition": {
			"resourceTypes": ["main_frame","sub_frame","stylesheet","script","image","font","object","xmlhttprequest","ping","csp_report","media","websocket","webtransport","webbundle","other"],
			"urlFilter": "yourlastdiet.today"
		 }
  }
]
